{
  "db_name": "PostgreSQL",
  "query": "SELECT skill_id, title, description, url_docs, image_src, progress, star, last_update\n               FROM skills ORDER BY star DESC, progress DESC",
  "describe": {
    "columns": [
      {
        "ordinal": 0,
        "name": "skill_id",
        "type_info": "Int4"
      },
      {
        "ordinal": 1,
        "name": "title",
        "type_info": "Text"
      },
      {
        "ordinal": 2,
        "name": "description",
        "type_info": "Text"
      },
      {
        "ordinal": 3,
        "name": "url_docs",
        "type_info": "Text"
      },
      {
        "ordinal": 4,
        "name": "image_src",
        "type_info": "Text"
      },
      {
        "ordinal": 5,
        "name": "progress",
        "type_info": "Int4"
      },
      {
        "ordinal": 6,
        "name": "star",
        "type_info": "Int4"
      },
      {
        "ordinal": 7,
        "name": "last_update",
        "type_info": "Timestamptz"
      }
    ],
    "parameters": {
      "Left": []
    },
    "nullable": [
      false,
      false,
      false,
      false,
      false,
      false,
      false,
      false
    ]
  },
  "hash": "d19a83f57e88fcdc5e2554e302cdd1c5d59557c3fcb6d017e3caaceec8499aef"
}
